maplibre/__future__/__init__.py
maplibre/__future__/controls.py
maplibre/__future__/datasets.py
maplibre/__future__/ipywidget.py
maplibre/__future__/layers.py
maplibre/__future__/pandas_ext.py
maplibre/__init__.py
maplibre/_constants.py
maplibre/_core.py
maplibre/_templates.py
maplibre/_utils.py
maplibre/abstracts.py
maplibre/basemaps.py
maplibre/colors.py
maplibre/config.py
maplibre/controls.py
maplibre/experimental.py
maplibre/express.py
maplibre/expressions.py
maplibre/ipywidget.py
maplibre/layer.py
maplibre/light.py
maplibre/map.py
maplibre/mapcontext.py
maplibre/plugins.py
maplibre/pmtiles_utils.py
maplibre/projection.py
maplibre/py.typed
maplibre/renderer.py
maplibre/shiny/__init__.py
maplibre/shiny/mapcontext.py
maplibre/shiny/renderer.py
maplibre/shiny/ui.py
maplibre/sky.py
maplibre/sources.py
maplibre/srcjs/ipywidget.css
maplibre/srcjs/ipywidget.js
maplibre/srcjs/ipywidget.maplibre-geocoder.css
maplibre/srcjs/maplibre-gl.css
maplibre/srcjs/maplibre-gl.js
maplibre/srcjs/pywidget.css
maplibre/srcjs/pywidget.js
maplibre/streamlit.py
maplibre/terrain.py
maplibre/types.py
maplibre/ui.py
maplibre/utils.py
maplibre-0.3.4.dist-info/LICENSE.md
maplibre-0.3.4.dist-info/METADATA
maplibre-0.3.4.dist-info/WHEEL
maplibre-0.3.4.dist-info/RECORD
