Metadata-Version: 2.1
Name: maplibre
Version: 0.3.4
Summary: Python bindings for MapLibre GL JS
License: MIT
Author: Stefan Kuethe
Author-email: stefan.kuethe@eoda.de
Requires-Python: >=3.9,<4
Classifier: License :: OSI Approved :: MIT License
Classifier: Programming Language :: Python :: 3
Classifier: Programming Language :: Python :: 3.9
Classifier: Programming Language :: Python :: 3.10
Classifier: Programming Language :: Python :: 3.11
Provides-Extra: all
Provides-Extra: anywidget
Provides-Extra: ipywidget
Provides-Extra: pmtiles
Provides-Extra: shiny
Requires-Dist: anywidget (>=0.9.0) ; extra == "all" or extra == "ipywidget" or extra == "anywidget"
Requires-Dist: branca
Requires-Dist: eval-type-backport
Requires-Dist: geopandas (>=0.14.2,<0.15.0) ; extra == "all"
Requires-Dist: htmltools (>=0.5.1) ; extra == "all" or extra == "shiny"
Requires-Dist: jinja2 (>=3.1.6)
Requires-Dist: pandas (>=2.1.4,<3.0.0) ; extra == "all"
Requires-Dist: pmtiles ; extra == "all" or extra == "pmtiles"
Requires-Dist: pydantic (>=2.5.3)
Requires-Dist: shiny (>0.7.0) ; extra == "all" or extra == "shiny"
Requires-Dist: traitlets ; extra == "all" or extra == "ipywidget" or extra == "anywidget"
